gregor/__init__.py
gregor/aggregate.py
gregor/cli.py
gregor/disaggregate.py
gregor/raster.py
gregor-0.0.2.dist-info/LICENSE.txt
gregor-0.0.2.dist-info/METADATA
gregor-0.0.2.dist-info/WHEEL
gregor-0.0.2.dist-info/entry_points.txt
gregor-0.0.2.dist-info/top_level.txt
gregor-0.0.2.dist-info/RECORD
