Metadata-Version: 2.1
Name: gregor
Version: 0.0.2
Summary: A library for spatial aggregation and disaggregation
Author-email: Jann Launer <j.a.c.launer@tudelft.nl>
Project-URL: changelog, https://github.com/jnnr/gregor/blob/main/CHANGELOG.md
Project-URL: homepage, https://gregor.readthedocs.io/en/latest/
Project-URL: repository, https://github.com/jnnr/gregor.git
Keywords: gis
Classifier: Programming Language :: Python :: 3.8
Classifier: Programming Language :: Python :: 3.9
Classifier: Programming Language :: Python :: 3.10
Classifier: Programming Language :: Python :: 3.11
Requires-Python: <4,>=3.8
License-File: LICENSE.txt
Requires-Dist: pandas>=1.2
Requires-Dist: numpy
Requires-Dist: matplotlib
Requires-Dist: geopandas
Requires-Dist: xarray
Requires-Dist: rasterio
Requires-Dist: rioxarray
Requires-Dist: rasterstats
Requires-Dist: click
